Workbook

Sheet Start here
A1: J.VARDHAN — CLIENT CEILING PRICE SHEET | B1: Fill the yellow cells. All prices are in INR (₹).
A2: What is the ceiling rate? | B2: Your genuine standard client-facing selling rate before any discount. Leave every unknown rate blank.
A3: છત ભાવ / મૂળ વેચાણ ભાવ | B3: ડિસ્કાઉન્ટ પહેલાંનો ક્લાયન્ટ માટેનો તમારો સામાન્ય ભાવ લખો. અજાણ્યો ભાવ ખાલી રાખો.
A4: 1 · Fill Rates | B4: Enter Ceiling rate INR (column F) for each service you offer. Zero means deliberately free; blank means not priced yet.
A5: 2 · Choose a unit | B5: Set the unit in E: package, event, person, item, day, hour, room, vehicle, trip, set, table, chair or sq ft. The web quantity multiplies this rate.
A6: 3 · Describe the scope | B6: In G, say what this price includes: size, guest count, duration, equipment, delivery, etc. Grouped checklist rows can be priced as one package.
A7: 4 · Package inclusions (optional) | B7: If a selected parent package covers this item, enter its C reference in H and the number of these units covered per parent unit in I. Extra units use this item's own rate.
A8: Inclusion example | B8: If a package includes 100 chairs, the chair row can name that package in H and 100 in I. This is an explanation only; no prices or inclusions are prefilled.
A9: 5 · Load online | B9: Save this .xlsx. On the checklist open Rates & downloads → Load prices and upload it. Review the import, then apply it. CSV from the Rates sheet also works.
A10: 6 · Make the offer | B10: Choose services online, enter quantities, then apply line discounts or a package discount. The review calculates the standard value, savings and offered estimate.
A11: Unpriced items | B11: The website shows a partial estimate until every chargeable selected item has a rate. It never substitutes zero for a blank price.
A12: Privacy | B12: Filled prices are read in the browser and saved on that device. Import does not upload or publish the workbook. Client draft exports include their pricing snapshot.
... A15: આગળની પ્રક્રિયા | B15: ભાવ ભરી Excel સાચવો, વેબપેજમાં અપલોડ કરો, જરૂરી વસ્તુઓ અને સંખ્યા પસંદ કરો, પછી ડિસ્કાઉન્ટ સાથે અંદાજ જુઓ.

Sheet Rates
A1: Ref | B1: Section | C1: Item English | D1: Item Gujarati | E1: Rate unit | F1: Ceiling rate INR | G1: Scope / inclusions | H1: Included under ref | I1: Units covered per parent | J1: Item ID
A2: C001 | B2: Shared arrangements & planning | C2: Venue selection & booking | D2: પ્રસંગના સ્થળની પસંદગી અને બુકિંગ | E2: package | J2: added-n01
A3: C002 | B3: Shared arrangements & planning | C3: Overall theme, decor design & setup plan | D3: સમગ્ર પ્રસંગની થીમ, સજાવટની ડિઝાઇન અને ગોઠવણનું આયોજન | E3: package | J3: added-n02
A4: C003 | B4: Shared arrangements & planning | C4: Destination wedding planning (optional) | D4: ડેસ્ટિનેશન વેડિંગનું આયોજન (જરૂર હોય તો) | E4: package | J4: added-n04
A5: C004 | B5: Shared arrangements & planning | C5: Ground & building lighting | D5: મેદાન અને બિલ્ડિંગની લાઇટિંગ | E5: package | J5: essentials-1-1
A6: C005 | B6: Shared arrangements & planning | C6: Mango-tree decoration | D6: આંબાના ઝાડની સજાવટ | E6: package | J6: essentials-1-2
A7: C006 | B7: Shared arrangements & planning | C7: Tree lighting | D7: ઝાડની લાઇટિંગ | E7: package | J7: essentials-1-3
A8: C007 | B8: Shared arrangements & planning | C8: Coolers, fans & heaters | D8: કૂલર, પંખા અને હીટર | E8: package | J8: essentials-1-4
A9: C008 | B9: Shared arrangements & planning | C9: Electrical outlets | D9: વીજળીના પ્લગ પોઇન્ટ | E9: package | J9: essentials-1-5
A10: C009 | B10: Shared arrangements & planning | C10: Mobile charging station | D10: મોબાઇલ ચાર્જિંગ પોઇન્ટ | E10: package | J10: essentials-1-6
A11: C010 | B11: Shared arrangements & planning | C11: Video crew tables & power | D11: વિડિયો ટીમ માટે ટેબલ અને વીજળી | E11: package | J11: essentials-1-7
A12: C011 | B12: Shared arrangements & planning | C12: Background music around the venue | D12: વેન્યુમાં બેકગ્રાઉન્ડ સંગીત | E12: package | J12: essentials-1-8
A13: C012 | B13: Shared arrangements & planning | C13: Silent generator | D13: સાઇલેન્ટ જનરેટર | E13: package | J13: essentials-1-9
... A201: C200 | B201: Other celebrations (optional) | C201: After-party planning | D201: આફ્ટર પાર્ટીનું આયોજન | E201: package | J201: added-n19

Sheet Sections
A1: Section | B1: Items | C1: Rates entered | D1: Still blank
A2: Shared arrangements & planning | B2: 38 | C2: =SUMPRODUCT((Rates!B$2:B$201=A2)*ISNUMBER(Rates!F$2:F$201)) | D2: =B2-C2
A3: Hospitality, stays & travel | B3: 29 | C3: =SUMPRODUCT((Rates!B$2:B$201=A3)*ISNUMBER(Rates!F$2:F$201)) | D3: =B3-C3
A4: Dining & beverages | B4: 17 | C4: =SUMPRODUCT((Rates!B$2:B$201=A4)*ISNUMBER(Rates!F$2:F$201)) | D4: =B4-C4
A5: Mandap Ropan | B5: 16 | C5: =SUMPRODUCT((Rates!B$2:B$201=A5)*ISNUMBER(Rates!F$2:F$201)) | D5: =B5-C5
A6: Mameru | B6: 10 | C6: =SUMPRODUCT((Rates!B$2:B$201=A6)*ISNUMBER(Rates!F$2:F$201)) | D6: =B6-C6
A7: Mehndi | B7: 8 | C7: =SUMPRODUCT((Rates!B$2:B$201=A7)*ISNUMBER(Rates!F$2:F$201)) | D7: =B7-C7
A8: Pithi / Haldi | B8: 14 | C8: =SUMPRODUCT((Rates!B$2:B$201=A8)*ISNUMBER(Rates!F$2:F$201)) | D8: =B8-C8
A9: Sangeet & Garba | B9: 24 | C9: =SUMPRODUCT((Rates!B$2:B$201=A9)*ISNUMBER(Rates!F$2:F$201)) | D9: =B9-C9
A10: Wedding, Baraat & Varmala | B10: 32 | C10: =SUMPRODUCT((Rates!B$2:B$201=A10)*ISNUMBER(Rates!F$2:F$201)) | D10: =B10-C10
A11: Reception | B11: 9 | C11: =SUMPRODUCT((Rates!B$2:B$201=A11)*ISNUMBER(Rates!F$2:F$201)) | D11: =B11-C11
A12: Other celebrations (optional) | B12: 3 | C12: =SUMPRODUCT((Rates!B$2:B$201=A12)*ISNUMBER(Rates!F$2:F$201)) | D12: =B12-C12
A13: TOTAL | B13: 200 | C13: =SUM(C2:C12) | D13: =SUM(D2:D12)
